soltrack/__init__.py
soltrack/data.py
soltrack/location.py
soltrack/position.py
soltrack/riseset.py
soltrack/time.py
soltrack-0.3.5.dist-info/licenses/LICENCE
soltrack-0.3.5.dist-info/METADATA
soltrack-0.3.5.dist-info/WHEEL
soltrack-0.3.5.dist-info/top_level.txt
soltrack-0.3.5.dist-info/RECORD
