Metadata-Version: 2.4
Name: soltrack
Version: 0.3.5
Summary: A free, fast and accurate Python package to compute the position of the Sun
Author-email: Marc van der Sluys <git@vandersluys.nl>
License-Expression: EUPL-1.2
Project-URL: SourceForge, https://soltrack.sourceforge.net
Project-URL: GitHub, https://github.com/MarcvdSluys/SolTrack-Python/
Project-URL: ReadTheDocs, https://soltrack.readthedocs.io
Keywords: astronomy,ephemeris,sun,solar,solar energy
Classifier: Development Status :: 4 - Beta
Classifier: Intended Audience :: Developers
Classifier: Intended Audience :: Education
Classifier: Intended Audience :: Science/Research
Classifier: Natural Language :: English
Classifier: Operating System :: OS Independent
Classifier: Programming Language :: Python :: 3
Classifier: Topic :: Scientific/Engineering
Classifier: Topic :: Scientific/Engineering :: Astronomy
Classifier: Topic :: Scientific/Engineering :: Physics
License-File: LICENCE
Requires-Dist: astroconst
Requires-Dist: astrotool
Requires-Dist: numpy
Requires-Dist: pandas
Dynamic: license-file
